lonlatProj/__init__.py
lonlatProj/utils.py
lonlatProj-0.0.0.26.dist-info/METADATA
lonlatProj-0.0.0.26.dist-info/WHEEL
lonlatProj-0.0.0.26.dist-info/top_level.txt
lonlatProj-0.0.0.26.dist-info/RECORD
