Metadata-Version: 2.1
Name: lonlatProj
Version: 0.0.0.26
Summary: lonlat_pred_utils
Home-page: https://github.com/qkdrk7777775
Author: chang je Cho
Author-email: qkdrk7777775@gmail.com
License: MIT
Platform: UNKNOWN
Requires-Dist: numpy
Requires-Dist: pandas
Requires-Dist: pyproj
Requires-Dist: netCDF4
Requires-Dist: rpy2
